caylent_devcontainer_cli/__init__.py
caylent_devcontainer_cli/__main__.py
caylent_devcontainer_cli/cli.py
caylent_devcontainer_cli/commands/__init__.py
caylent_devcontainer_cli/commands/code.py
caylent_devcontainer_cli/commands/env.py
caylent_devcontainer_cli/commands/install.py
caylent_devcontainer_cli/commands/setup.py
caylent_devcontainer_cli/commands/setup_interactive.py
caylent_devcontainer_cli/commands/template.py
caylent_devcontainer_cli/utils/__init__.py
caylent_devcontainer_cli/utils/constants.py
caylent_devcontainer_cli/utils/env.py
caylent_devcontainer_cli/utils/fs.py
caylent_devcontainer_cli/utils/ui.py
caylent_devcontainer_cli/utils/version.py
caylent_devcontainer_cli-1.14.1.dist-info/METADATA
caylent_devcontainer_cli-1.14.1.dist-info/WHEEL
caylent_devcontainer_cli-1.14.1.dist-info/entry_points.txt
caylent_devcontainer_cli-1.14.1.dist-info/top_level.txt
caylent_devcontainer_cli-1.14.1.dist-info/RECORD
