Metadata-Version: 2.4
Name: caylent-devcontainer-cli
Version: 1.14.1
Summary: CLI tool for managing Caylent devcontainers
Author-email: Caylent <solutions-owners@caylent.com>
License-Expression: Apache-2.0
Project-URL: Homepage, https://github.com/caylent-solutions/devcontainer
Project-URL: Issues, https://github.com/caylent-solutions/devcontainer/issues
Classifier: Development Status :: 4 - Beta
Classifier: Intended Audience :: Developers
Classifier: Programming Language :: Python :: 3
Classifier: Programming Language :: Python :: 3.8
Classifier: Programming Language :: Python :: 3.9
Classifier: Programming Language :: Python :: 3.10
Classifier: Programming Language :: Python :: 3.11
Classifier: Programming Language :: Python :: 3.12
Requires-Python: >=3.8
Requires-Dist: black~=24.0
Requires-Dist: flake8~=7.0
Requires-Dist: isort~=6.0
Requires-Dist: pytest~=7.0
Requires-Dist: pytest-cov~=4.0
Requires-Dist: questionary~=2.0.0
Requires-Dist: semver~=3.0.0
